llmbot_plugin_bilisearch-0.2.0.dist-info/METADATA
llmbot_plugin_bilisearch-0.2.0.dist-info/WHEEL
llmbot_plugin_bilisearch-0.2.0.dist-info/entry_points.txt
llmbot_plugin_bilisearch-0.2.0.dist-info/licenses/LICENSE
llmbot_plugin_bilisearch/__init__.py
llmbot_plugin_bilisearch-0.2.0.dist-info/RECORD
