Metadata-Version: 2.1
Name: llmbot_plugin_bilisearch
Version: 0.2.0
Summary: LLMBOT PLUGIN
Author-Email: sudoskys <coldlando@hotmail.com>
License: MIT
Requires-Python: <3.12,>=3.9
Requires-Dist: bilibili-api-python>=16.2.0
